werkflow_file/__init__.py
werkflow_file/file.py
werkflow_file-0.1.6.dist-info/licenses/LICENSE
werkflow_file-0.1.6.dist-info/METADATA
werkflow_file-0.1.6.dist-info/WHEEL
werkflow_file-0.1.6.dist-info/top_level.txt
werkflow_file-0.1.6.dist-info/RECORD
